MANIFEST.in
README.rst
setup.py
committees/__init__.py
committees/admin.py
committees/managers.py
committees/models.py
committees/tests.py
committees/urls.py
committees/views.py
committees/templates/committees/base.html
committees/templates/committees/group_detail.html
committees/templates/committees/index.html
committees/templates/committees/meeting_detail.html
committees/templates/committees/minutes_detail.html
committees/templates/committees/sermon_detail.html
committees/templates/committees/term_detail.html
committees/templatetags/__init__.py
committees/templatetags/__init__.pyc
committees/templatetags/committee_tags.py
django_committees.egg-info/PKG-INFO
django_committees.egg-info/SOURCES.txt
django_committees.egg-info/dependency_links.txt
django_committees.egg-info/requires.txt
django_committees.egg-info/top_level.txt
django_committees.egg-info/zip-safe